Excelutilities/__init__.py
Excelutilities/attach_data.py
Excelutilities/importing_data_helpers.py
Excelutilities/index_helpers.py
Excelutilities/worksheet_remove_data.py
Excelutilities/cleaning_utilities/__init__.py
Excelutilities/cleaning_utilities/tests_worksheet_cleaning_utilities.py
Excelutilities/cleaning_utilities/worksheet_cleaning_utilities.py
Excelutilities/tests/__init__.py
Excelutilities/tests/index_helpers_tests.py
Excelutilities/tests/workbook_similarity_measures_tests.py
Excelutilities/weird_to_standard/__init__.py
Excelutilities/weird_to_standard/weird_to_standard1/__init__.py
Excelutilities/weird_to_standard/weird_to_standard1/test_weird_to_standard1.py
Excelutilities/weird_to_standard/weird_to_standard1/weird_to_standard1.py
Excelutilities/workbook_debugging/__init__.py
Excelutilities/workbook_debugging/interactive_wb_debugging_tools.py
Excelutilities/workbook_debugging/tests_interactive_wb_debugging_tools.py
Excelutilities/workbook_debugging/workbook_similarity_measures.py
Excelutilities-0.0.11.dist-info/METADATA
Excelutilities-0.0.11.dist-info/WHEEL
Excelutilities-0.0.11.dist-info/top_level.txt
Excelutilities-0.0.11.dist-info/RECORD
