Metadata-Version: 2.1
Name: Excelutilities
Version: 0.0.11
Summary: Useful functions for writing code for Excel applications
Home-page: https://github.com/EthanTheMathmo/excel-utilities/
Author: Ethan Horsfall
Author-email: ethan.horsfall@gmail.com
License: UNKNOWN
Platform: UNKNOWN
Classifier: Programming Language :: Python :: 3.8
Classifier: License :: OSI Approved :: GNU General Public License v3 (GPLv3)
Requires-Dist: PySimpleGUI (>=4.0.0)
Requires-Dist: xlwings (>=0.24.0)
Requires-Dist: openpyxl (>=3.0.0)
Requires-Dist: numpy (>=1.20.0)
Requires-Dist: jellyfish (>=0.8.8)
